{
  "id": "vesneabm",
  "profilePicture": "PFP_VesneaBM.png",
  "profilePicture2": "PFP_VesneaBM.png",
  "name": "Vesnea",
  "alternateName": "Blossom Mode",
  "genderColor": "Female",
  "attributes": ["Magical", "Nature"],

  "artworks": [
    {
      "src": "V01.jpg",
      "title": "V01",
      "caption": {
        "en": "Vesnea Blossom Mode's reference sheet.",
        "jp": "VesneaのBlossom Modeの設定資料です。"
      }
    },
    {
      "src": "S165 - Vesnea Blossom Mode.jpg",
      "title": "S165 - Vesnea Blossom Mode",
      "caption": {
        "en": "Vesnea Blossom Mode.",
        "jp": "VesneaのBlossom Mode。"
      }
    }
  ],
  "tradearts": [
    {
      "src": "",
      "title": "",
      "caption": { "en": "", "jp": "" }
    }
  ],
  "collabarts": [
    {
      "src": "",
      "title": "",
      "caption": { "en": "", "jp": "" }
    }
  ],
  "giftarts": [
    {
      "src": "",
      "title": "",
      "caption": { "en": "", "jp": "" }
    }
  ],
  "commarts": [
    {
      "src": "by Haineko - 20250300.webp",
      "title": "by Haineko (March 2025)",
      "caption": { "en": "", "jp": "" }
    },
    {
      "src": "by Haineko - 20251225.webp",
      "title": "by Haineko (25 December 2025)",
      "caption": { "en": "", "jp": "" }
    }
  ]
}
